hashdex/__init__.py
hashdex/cli.py
hashdex/files.py
hashdex/indexer.py
hashdex-0.7.0.dist-info/AUTHORS.rst
hashdex-0.7.0.dist-info/LICENSE
hashdex-0.7.0.dist-info/METADATA
hashdex-0.7.0.dist-info/WHEEL
hashdex-0.7.0.dist-info/entry_points.txt
hashdex-0.7.0.dist-info/top_level.txt
hashdex-0.7.0.dist-info/RECORD
