Metadata-Version: 2.1
Name: hashdex
Version: 0.7.0
Summary: A file indexer based on content hashes
Home-page: https://github.com/jeff-99/hashdex
Author: Jeffrey Slort
Author-email: j_slort@hotmail.com
License: MIT license
Keywords: hashdex
Platform: UNKNOWN
Classifier: Development Status :: 4 - Beta
Classifier: Intended Audience :: Developers
Classifier: License :: OSI Approved :: MIT License
Classifier: Natural Language :: English
Classifier: Programming Language :: Python :: 2.7
Classifier: Programming Language :: Python :: 3
Classifier: Programming Language :: Python :: 3.4
Classifier: Programming Language :: Python :: 3.5
Classifier: Programming Language :: Python :: 3.6
Classifier: Topic :: Utilities
Requires-Dist: Click (>=6.7)
